tera_rag/__init__.py
tera_rag/version.py
tera_rag-0.0.0.dist-info/LICENSE
tera_rag-0.0.0.dist-info/METADATA
tera_rag-0.0.0.dist-info/WHEEL
tera_rag-0.0.0.dist-info/entry_points.txt
tera_rag-0.0.0.dist-info/top_level.txt
tera_rag-0.0.0.dist-info/RECORD
